testly/__init__.py
testly/__main__.py
testly/behaviour.py
testly/config.txt
testly/database.py
testly/rest.py
testly/soap.py
testly/utilities.py
testly-1.0.3.dist-info/LICENSE
testly-1.0.3.dist-info/METADATA
testly-1.0.3.dist-info/WHEEL
testly-1.0.3.dist-info/entry_points.txt
testly-1.0.3.dist-info/top_level.txt
testly-1.0.3.dist-info/RECORD
