Metadata-Version: 2.1
Name: testly
Version: 1.0.3
Summary: Perform SOAP and REST test
Home-page: https://github.com/stewiejnr/testly
Author: Stewartium, RPhipps
Author-email: stewartium1@gmail.com,rhadjni@hotmail.com
License: MIT
Platform: UNKNOWN
Classifier: License :: OSI Approved :: MIT License
Classifier: Programming Language :: Python :: 3
Classifier: Programming Language :: Python :: 3.7
Classifier: Programming Language :: Python :: Implementation :: PyPy
Requires-Dist: requests
Requires-Dist: zeep
Requires-Dist: pyyaml
